incatools/odk/__init__.py
incatools/odk/activate.jinja2
incatools/odk/cli.py
incatools/odk/config.py
incatools/odk/helper.py
incatools/odk/model.py
incatools/odk/setup.py
incatools/odk/template.py
incatools/odk/templates/.gitignore.jinja2
incatools/odk/templates/CONTRIBUTING.md.jinja2
incatools/odk/templates/README.md.jinja2
incatools/odk/templates/_dynamic_documentation.jinja2
incatools/odk/templates/_dynamic_files.jinja2
incatools/odk/templates/_dynamic_sparql.jinja2
incatools/odk/templates/_dynamic_workflows.jinja2
incatools/odk/templates/issue_template.md.jinja2
incatools/odk/templates/src/ontology/Makefile.jinja2
incatools/odk/templates/src/ontology/README-editors.md.jinja2
incatools/odk/templates/src/ontology/catalog-v001.xml.jinja2
incatools/odk/templates/src/ontology/profile.txt
incatools/odk/templates/src/ontology/run.bat.jinja2
incatools/odk/templates/src/ontology/run.sh.jinja2
incatools/odk/templates/src/ontology/tmp/.gitkeep
incatools/odk/templates/src/scripts/run-command.sh
incatools/odk/templates/src/sparql/README.md.jinja2
incatools/odk/templates/src/sparql/basic-report.sparql
incatools/odk/templates/src/sparql/class-count-by-prefix.sparql
incatools/odk/templates/src/sparql/edges.sparql
incatools/odk/templates/src/sparql/obsoletes.sparql
incatools/odk/templates/src/sparql/postprocess-module.ru
incatools/odk/templates/src/sparql/preprocess-module.ru
incatools/odk/templates/src/sparql/simple-seed.sparql
incatools/odk/templates/src/sparql/subsets-labeled.sparql
incatools/odk/templates/src/sparql/synonyms.sparql
incatools/odk/templates/src/sparql/terms.sparql
incatools/odk/templates/src/sparql/xrefs.sparql
incatools/odk/util.py
odk_core-0.1.2.dist-info/WHEEL
odk_core-0.1.2.dist-info/entry_points.txt
odk_core-0.1.2.dist-info/METADATA
odk_core-0.1.2.dist-info/RECORD
