Metadata-Version: 2.4
Name: odk-core
Version: 0.1.2
Summary: Ontology Development Kit Core
Author: Damien Goutte-Gattat, Nicolas Matentzoglu
Author-email: Damien Goutte-Gattat <dgouttegattat@incenp.org>, Nicolas Matentzoglu <nicolas.matentzoglu@gmail.com>
License-Expression: BSD-3-Clause
Classifier: Development Status :: 1 - Planning
Classifier: Environment :: Console
Classifier: Intended Audience :: Science/Research
Classifier: Topic :: Scientific/Engineering
Requires-Dist: click
Requires-Dist: dacite
Requires-Dist: dataclasses-json
Requires-Dist: dataclasses-jsonschema
Requires-Dist: defusedxml
Requires-Dist: jinja2
Requires-Dist: pyyaml
Requires-Dist: babelon ; extra == 'workflows'
Requires-Dist: dosdp ; extra == 'workflows'
Requires-Dist: lightrdf ; extra == 'workflows'
Requires-Dist: semsql ; extra == 'workflows'
Requires-Dist: sssom ; extra == 'workflows'
Requires-Dist: tsvalid ; extra == 'workflows'
Requires-Python: >=3.9
Project-URL: Homepage, http://incatools.github.io/ontology-development-kit
Project-URL: Repository, https://github.com/gouttegd/odkcore
Provides-Extra: workflows
